[
  {
    "id": 1,
    "title": "Beyond Take Off: From Local Youth Work to Cross Border Connections",
    "deadline": "2026-06-28",
    "type": "Offline",
    "location": "Gürcüstan",
    "applyLink": "http://trainings.salto-youth.net/14941",
    "publishedAt": "2026-08-07",
    "tags": [
      "Offline",
      "Gürcüstan"
    ]
  },
  {
    "id": 2,
    "title": "Europe as a Resource for Local Youth Work",
    "deadline": "2026-06-28",
    "type": "Offline",
    "location": "Estoniya",
    "applyLink": "http://trainings.salto-youth.net/14994",
    "publishedAt": "2026-07-17",
    "tags": [
      "Offline",
      "Estoniya"
    ]
  },
  {
    "id": 3,
    "title": "Strengthening Local Youth Councils in the AI age",
    "deadline": "2026-06-28",
    "type": "Offline",
    "location": "İspaniya",
    "applyLink": "http://trainings.salto-youth.net/14970",
    "publishedAt": "2026-07-03",
    "tags": [
      "Offline",
      "İspaniya"
    ]
  },
  {
    "id": 4,
    "title": "Connect & Create: KA220 Partnership Lab",
    "deadline": "2026-06-28",
    "type": "Offline",
    "location": "Polşa",
    "applyLink": "http://trainings.salto-youth.net/14971",
    "publishedAt": "2026-07-17",
    "tags": [
      "Offline",
      "Polşa"
    ]
  },
  {
    "id": 5,
    "title": "Exchange Forum on the European Youth Work Agenda: Boosting national processes for youth work development",
    "deadline": "2026-06-28",
    "type": "Offline",
    "location": "Slovenia",
    "applyLink": "http://trainings.salto-youth.net/14958",
    "publishedAt": "2026-09-03",
    "tags": [
      "Offline",
      "Slovenia"
    ]
  },
  {
    "id": 6,
    "title": "Supporting ESC Volunteers through Mentoring Training Course",
    "deadline": "2026-06-28",
    "type": "Offline",
    "location": "Tunis",
    "applyLink": "http://trainings.salto-youth.net/14895",
    "publishedAt": "2026-07-15",
    "tags": [
      "Offline",
      "Tunis"
    ]
  },
  {
    "id": 7,
    "title": "Youth@Work Conference: Value and Recognition of Youth Work for Employability and Entrepreneurship",
    "deadline": "2026-06-30",
    "type": "Offline",
    "location": "Gürcüstan",
    "applyLink": "http://trainings.salto-youth.net/14923",
    "publishedAt": "2026-07-16",
    "tags": [
      "Offline",
      "Gürcüstan"
    ]
  },
  {
    "id": 8,
    "title": "Transforming Challenges into Shared Happiness",
    "deadline": "2026-07-02",
    "type": "Online",
    "location": "İtaliya",
    "applyLink": "http://trainings.salto-youth.net/14992",
    "publishedAt": "2026-07-03",
    "tags": [
      "Online",
      "İtaliya"
    ]
  },
  {
    "id": 9,
    "title": "Pathways to Accessible Youth Work - Online Conference",
    "deadline": "2026-07-05",
    "type": "Online",
    "location": "Macarıstan",
    "applyLink": "http://trainings.salto-youth.net/14978",
    "publishedAt": "2026-07-06",
    "tags": [
      "Online",
      "Macarıstan"
    ]
  },
  {
    "id": 10,
    "title": "PlayLab: Building Communities Through Experience",
    "deadline": "2026-07-05",
    "type": "Offline",
    "location": "Polşa",
    "applyLink": "http://trainings.salto-youth.net/14950",
    "publishedAt": "2026-07-15",
    "tags": [
      "Offline",
      "Polşa"
    ]
  },
  {
    "id": 11,
    "title": "Organizational development for preparedness: Fostering resilience in youth NGOs",
    "deadline": "2026-07-05",
    "type": "Offline",
    "location": "İspaniya",
    "applyLink": "http://trainings.salto-youth.net/15015",
    "publishedAt": "2026-07-30",
    "tags": [
      "Offline",
      "İspaniya"
    ]
  },
  {
    "id": 12,
    "title": "Online FREE International Virtual Exchange – Value Proposition Development, Market Research and Customer Analysis",
    "deadline": "2026-07-06",
    "type": "Online",
    "location": "İtaliya",
    "applyLink": "http://trainings.salto-youth.net/15007",
    "publishedAt": "2026-07-07",
    "tags": [
      "Online",
      "İtaliya"
    ]
  },
  {
    "id": 13,
    "title": "Debunker Summer School of Media Literacy | NECE Lab",
    "deadline": "2026-07-08",
    "type": "Offline",
    "location": "Çexiya",
    "applyLink": "http://trainings.salto-youth.net/15030",
    "publishedAt": "2026-07-14",
    "tags": [
      "Offline",
      "Çexiya"
    ]
  },
  {
    "id": 14,
    "title": "FINAL CONFERENCE \"Participation Needs Nonviolent Debate for Conflict Transformation\"",
    "deadline": "2026-07-13",
    "type": "Offline",
    "location": "İsveç",
    "applyLink": "http://trainings.salto-youth.net/14995",
    "publishedAt": "2026-07-16",
    "tags": [
      "Offline",
      "İsveç"
    ]
  },
  {
    "id": 15,
    "title": "Mindful Impact: Strengthening Youth Work From Within",
    "deadline": "2026-07-17",
    "type": "Offline",
    "location": "Gürcüstan",
    "applyLink": "http://trainings.salto-youth.net/14990",
    "publishedAt": "2026-07-27",
    "tags": [
      "Offline",
      "Gürcüstan"
    ]
  },
  {
    "id": 16,
    "title": "VIRTUALLYEDU – Virtual Exchanges and Education on Digital Skill",
    "deadline": "2026-07-19",
    "type": "Online",
    "location": "İsveç",
    "applyLink": "http://trainings.salto-youth.net/14989",
    "publishedAt": "2026-07-20",
    "tags": [
      "Online",
      "İsveç"
    ]
  },
  {
    "id": 17,
    "title": "Digital Tools for Autism Inclusion: Supporting Youth Workers, NGOs and Caregivers Through Coordinated Care",
    "deadline": "2026-07-22",
    "type": "Online",
    "location": "Livan",
    "applyLink": "http://trainings.salto-youth.net/14997",
    "publishedAt": "2026-07-18",
    "tags": [
      "Online",
      "Livan"
    ]
  },
  {
    "id": 18,
    "title": "Virtual Partnership Building Activity (PBA) for Erasmus+ KA152 & KA153 Projects Vol. 4",
    "deadline": "2026-07-27",
    "type": "Online",
    "location": "Gürcüstan",
    "applyLink": "http://trainings.salto-youth.net/15029",
    "publishedAt": "2026-07-29",
    "tags": [
      "Online",
      "Gürcüstan"
    ]
  },
  {
    "id": 19,
    "title": "STEAM in Youth Work: Creative projects for young people",
    "deadline": "2026-07-27",
    "type": "Online",
    "location": "Yunanistan",
    "applyLink": "http://trainings.salto-youth.net/15026",
    "publishedAt": "2026-08-10",
    "tags": [
      "Online",
      "Yunanistan"
    ]
  },
  {
    "id": 20,
    "title": "Sapounofouska Playful Learning Fest",
    "deadline": "2026-07-28",
    "type": "Offline",
    "location": "Yunanistan",
    "applyLink": "http://trainings.salto-youth.net/14945",
    "publishedAt": "2026-08-11",
    "tags": [
      "Offline",
      "Yunanistan"
    ]
  },
  {
    "id": 21,
    "title": "Inclusive Evolution: The Next Generation 2026",
    "deadline": "2026-07-30",
    "type": "Offline",
    "location": "Macarıstan",
    "applyLink": "http://trainings.salto-youth.net/14838",
    "publishedAt": "2026-08-05",
    "tags": [
      "Offline",
      "Macarıstan"
    ]
  },
  {
    "id": 22,
    "title": "Robotics in Youth Work: From Playful Missions to Real Skills",
    "deadline": "2026-07-31",
    "type": "Online",
    "location": "Yunanistan",
    "applyLink": "http://trainings.salto-youth.net/15031",
    "publishedAt": "2026-08-08",
    "tags": [
      "Online",
      "Yunanistan"
    ]
  },
  {
    "id": 23,
    "title": "Ask Better, Teach Better: Question‑driven AI & advocacy in youth work",
    "deadline": "2026-07-31",
    "type": "Online",
    "location": "Yunanistan",
    "applyLink": "http://trainings.salto-youth.net/15018",
    "publishedAt": "2026-08-05",
    "tags": [
      "Online",
      "Yunanistan"
    ]
  },
  {
    "id": 24,
    "title": "TOSCA Volunteering – Training and Support for Organisations in the European Solidarity Corps",
    "deadline": "2026-08-03",
    "type": "Offline",
    "location": "Çexiya",
    "applyLink": "http://trainings.salto-youth.net/15021",
    "publishedAt": "2026-08-19",
    "tags": [
      "Offline",
      "Çexiya"
    ]
  },
  {
    "id": 25,
    "title": "Volunteering Teams as a Tool to support Inclusion",
    "deadline": "2026-08-09",
    "type": "Offline",
    "location": "Finlandiya",
    "applyLink": "http://trainings.salto-youth.net/14954",
    "publishedAt": "2026-08-26",
    "tags": [
      "Offline",
      "Finlandiya"
    ]
  },
  {
    "id": 26,
    "title": "PBA Youth X Culture",
    "deadline": "2026-08-15",
    "type": "Offline",
    "location": "Belçika",
    "applyLink": "http://trainings.salto-youth.net/14904",
    "publishedAt": "2026-09-09",
    "tags": [
      "Offline",
      "Belçika"
    ]
  },
  {
    "id": 27,
    "title": "Working with Queer Youth",
    "deadline": "2026-08-30",
    "type": "Offline",
    "location": "İsveç",
    "applyLink": "http://trainings.salto-youth.net/14859",
    "publishedAt": "2026-09-14",
    "tags": [
      "Offline",
      "İsveç"
    ]
  },
  {
    "id": 28,
    "title": "Outdoor Paths: Designing Experiential Activities for Young People",
    "deadline": "2026-07-31",
    "type": "Online",
    "location": "Yunanistan",
    "applyLink": "http://trainings.salto-youth.net/15032",
    "publishedAt": "2026-09-02",
    "tags": [
      "Online",
      "Yunanistan"
    ]
  },
  {
    "id": 29,
    "title": "Play to Learn: Creating Educational Games for Youth Work",
    "deadline": "2026-07-31",
    "type": "Online",
    "location": "Yunanistan",
    "applyLink": "http://trainings.salto-youth.net/15033",
    "publishedAt": "2026-09-02",
    "tags": [
      "Online",
      "Yunanistan"
    ]
  },
  {
    "id": 30,
    "title": "Engaging Communities Through Sustainable Sport Communication",
    "deadline": "2026-09-01",
    "type": "Online",
    "location": "Xorvatiya",
    "applyLink": "http://trainings.salto-youth.net/14998",
    "publishedAt": "2026-09-15",
    "tags": [
      "Online",
      "Xorvatiya"
    ]
  },
  {
    "id": 31,
    "title": "Mentoring under construction - Focus Mentoring training based on the Mentoring framework",
    "deadline": "2026-09-06",
    "type": "Offline",
    "location": "Polşa",
    "applyLink": "http://trainings.salto-youth.net/14983",
    "publishedAt": "2026-09-21",
    "tags": [
      "Offline",
      "Polşa"
    ]
  },
  {
    "id": 32,
    "title": "Why municipal youth participation?",
    "deadline": "2026-09-06",
    "type": "Offline",
    "location": "Macarıstan",
    "applyLink": "http://trainings.salto-youth.net/14905",
    "publishedAt": "2026-09-18",
    "tags": [
      "Offline",
      "Macarıstan"
    ]
  }
]